toyota_na_custom/__init__.py
toyota_na_custom/app.py
toyota_na_custom/auth.py
toyota_na_custom/client.py
toyota_na_custom/exceptions.py
toyota_na_custom/vehicle/__init__.py
toyota_na_custom/vehicle/base_vehicle.py
toyota_na_custom/vehicle/vehicle.py
toyota_na_custom/vehicle/entity_types/ToyotaLocation.py
toyota_na_custom/vehicle/entity_types/ToyotaLockableOpening.py
toyota_na_custom/vehicle/entity_types/ToyotaNumeric.py
toyota_na_custom/vehicle/entity_types/ToyotaOpening.py
toyota_na_custom/vehicle/entity_types/ToyotaRemoteStart.py
toyota_na_custom/vehicle/entity_types/__init__.py
toyota_na_custom/vehicle/vehicle_generations/__init__.py
toyota_na_custom/vehicle/vehicle_generations/seventeen_cy.py
toyota_na_custom/vehicle/vehicle_generations/seventeen_cy_plus.py
ipython_personal_utils-0.0.10.dist-info/METADATA
ipython_personal_utils-0.0.10.dist-info/WHEEL
ipython_personal_utils-0.0.10.dist-info/top_level.txt
ipython_personal_utils-0.0.10.dist-info/RECORD
